Workbook

Sheet Students
A1: Student_ID | B1: Admission_Number | C1: First_Name | D1: Middle_Name | E1: Last_Name | F1: Gender | G1: DOB | H1: Age | I1: Blood_Group | J1: Class | K1: Admission_Date | L1: Student_Status | M1: Guardian_Name | N1: Relationship | O1: Phone | P1: Email | Q1: Home_Address | R1: Hostel | S1: Special_Needs
A2: 1 | B2: CIA001 | C2: Josiah | D2: Muyiwa | E2: Ojo | F2: Male | G2: 40487 | H2: =IF(DATEDIF(G2, TODAY(), "y")=0,"",DATEDIF(G2, TODAY(), "y")&"years, ")&IF(DATEDIF(G2, TODAY(), "ym")=0,"",DATEDIF(G2, TODAY(), "ym")&"months, ")&IF(DATEDIF(G2, TODAY(), "md")=0,"",DATEDIF(G2, TODAY(), "md")&"days") -> 15years, 1months, 22days | I2: O+ | J2: JSS1 | K2: 45674 | L2: Graduated | M2: Ojo Omowumi | N2: Mother | O2: 7041979491 | P2: jolectro777@gmail.com | Q2: 19 Aleniboro Street, Offa garage, Iorin | R2: Yes | S2: Loves Food

Sheet Teachers
A1: Teacher_ID | B1: Staff_Number | C1: Full_Name | D1: Gender | E1: Qualification | F1: Subject_Specialization | G1: Class_Teacher | H1: Class_Assigned | I1: Employment_Type | J1: Date_Employed | K1: Phone | L1: Email | M1: Status
A2: TUT001 | B2: 1 | C2: Jolectro | D2: Male | E2: Ph.D | F2: Quantum Mathematics | G2: No | H2: JSS1 | I2: Part Time | J2: 43689 | K2: 7041979491 | L2: jolectro777@gmail.com | M2: On Leave
A3: TUT002 | B3: 2 | C3: Susana | D3: Female | E3: Queen | F3: Linguistics | G3: Yes | H3: JSS2 | I3: Full Time | J3: 22262 | K3: 7041979491 | L3: jolectro777@gmail.com | M3: On Duty

Sheet Subjects
A1: Subject_ID | B1: Subject_Name | C1: Department | D1: Class | E1: Weekly_Periods | F1: Teacher_ID | G1: Teacher Name
A2: MAT001 | B2: Mathematics | C2: General | D2: JSS1 | E2: 10 | F2: TUT001 | G2: =_xlfn.XLOOKUP(Subject[[#This Row],[Teacher_ID]],Teachers!A:A,Teachers!C:C) -> Jolectro
A3: ENG001 | B3: English | C3: General | D3: JSS1 | E3: 10 | F3: TUT002 | G3: =_xlfn.XLOOKUP(Subject[[#This Row],[Teacher_ID]],Teachers!A:A,Teachers!C:C) -> Susana
A4: SCI001 | B4: Science | C4: General | D4: JSS1 | E4: 7 | F4: TUT001 | G4: =_xlfn.XLOOKUP(Subject[[#This Row],[Teacher_ID]],Teachers!A:A,Teachers!C:C) -> Jolectro
A5: COM001 | B5: Computer | C5: General | D5: JSS1 | E5: 5 | F5: TUT002 | G5: =_xlfn.XLOOKUP(Subject[[#This Row],[Teacher_ID]],Teachers!A:A,Teachers!C:C) -> Susana
A6: MUS001 | B6: Music | C6: Arts | D6: JSS1 | E6: 3 | F6: TUT002 | G6: =_xlfn.XLOOKUP(Subject[[#This Row],[Teacher_ID]],Teachers!A:A,Teachers!C:C) -> Susana
G7: =_xlfn.XLOOKUP(Subject[[#This Row],[Teacher_ID]],Teachers!A:A,Teachers!C:C) -> 0
G8: =_xlfn.XLOOKUP(Subject[[#This Row],[Teacher_ID]],Teachers!A:A,Teachers!C:C) -> 0
G9: =_xlfn.XLOOKUP(Subject[[#This Row],[Teacher_ID]],Teachers!A:A,Teachers!C:C) -> 0
G10: =_xlfn.XLOOKUP(Subject[[#This Row],[Teacher_ID]],Teachers!A:A,Teachers!C:C) -> 0
G11: =_xlfn.XLOOKUP(Subject[[#This Row],[Teacher_ID]],Teachers!A:A,Teachers!C:C) -> 0
G12: =_xlfn.XLOOKUP(Subject[[#This Row],[Teacher_ID]],Teachers!A:A,Teachers!C:C) -> 0
G13: =_xlfn.XLOOKUP(Subject[[#This Row],[Teacher_ID]],Teachers!A:A,Teachers!C:C) -> 0
G14: =_xlfn.XLOOKUP(Subject[[#This Row],[Teacher_ID]],Teachers!A:A,Teachers!C:C) -> 0
G15: =_xlfn.XLOOKUP(Subject[[#This Row],[Teacher_ID]],Teachers!A:A,Teachers!C:C) -> 0
G16: =_xlfn.XLOOKUP(Subject[[#This Row],[Teacher_ID]],Teachers!A:A,Teachers!C:C) -> 0
G17: =_xlfn.XLOOKUP(Subject[[#This Row],[Teacher_ID]],Teachers!A:A,Teachers!C:C) -> 0
G18: =_xlfn.XLOOKUP(Subject[[#This Row],[Teacher_ID]],Teachers!A:A,Teachers!C:C) -> 0
... G101: =_xlfn.XLOOKUP(Subject[[#This Row],[Teacher_ID]],Teachers!A:A,Teachers!C:C) -> 0

Sheet Class
A1: Class_ID | B1: Class_Name | C1: Class_Teacher_ID | D1: Total_Students | E1: Room_Number
A2: 1 | B2: JSS1 | C2: TUT001 | D2: =COUNTIF(Students!J:J,Class[[#This Row],[Class_Name]]) -> 1
A3: 2 | B3: JSS2 | C3: TUT002 | D3: =COUNTIF(Students!J:J,#REF!) -> 0
D4: =COUNTIF(Students!J:J,#REF!) -> 0
D5: =COUNTIF(Students!J:J,#REF!) -> 0
D6: =COUNTIF(Students!J:J,#REF!) -> 0
D7: =COUNTIF(Students!J:J,#REF!) -> 0
D8: =COUNTIF(Students!J:J,#REF!) -> 0
D9: =COUNTIF(Students!J:J,#REF!) -> 0
D10: =COUNTIF(Students!J:J,#REF!) -> 0
D11: =COUNTIF(Students!J:J,#REF!) -> 0
D12: =COUNTIF(Students!J:J,#REF!) -> 0
D13: =COUNTIF(Students!J:J,#REF!) -> 0
D14: =COUNTIF(Students!J:J,#REF!) -> 0
D15: =COUNTIF(Students!J:J,#REF!) -> 0
... D101: =COUNTIF(Students!J:J,#REF!) -> 0

Sheet Brushsheet
A1: Student ID | B1: Student Name | C1: Class | D1: Subject ID | E1: Subject Name | F1: Term | G1: 1st CA | H1: 2nd CA | I1: Assignment | J1: Exam Score | K1: Total | L1: Grade | M1: Remark
A2: 1 | B2: =CONCATENATE(_xlfn.XLOOKUP(Brushsheet[[#This Row],[Student ID]],Students!A:A,Students!E:E)," ",_xlfn.XLOOKUP(Brushsheet[[#This Row],[Student ID]],Students!A:A,Students!C:C)," ",_xlfn.XLOOKUP(Brushsheet[[#This Row],[Student ID]],Students!A:A,Students!D:D)) -> Ojo Josiah Muyiwa | C2: =_xlfn.XLOOKUP(Brushsheet[[#This Row],[Student ID]],Students!A:A,Students!J:J) -> JSS1 | D2: MAT001 | E2: =_xlfn.XLOOKUP(Brushsheet[[#This Row],[Subject ID]],Subjects!A:A,Subjects!B:B) -> Mathematics | F2: 1st | G2: 12 | H2: 13 | I2: 8 | J2: 53 | K2: =SUM(Brushsheet[[#This Row],[1st CA]:[Exam Score]]) -> 86 | L2: =IF(Brushsheet[[#This Row],[Total]]>=70,"A",IF(Brushsheet[[#This Row],[Total]]>=60,"B",IF(Brushsheet[[#This Row],[Total]]>=50,"C",IF(Brushsheet[[#This Row],[Total]]>=45,"D",IF(Brushsheet[[#This Row],[Total]]>=40,"E","F"))))) -> A | M2: =IF(Brushsheet[[#This Row],[Total]]>=70,"Excellent",IF(Brushsheet[[#This Row],[Total]]>=60,"V.Good",IF(Brushsheet[[#This Row],[Total]]>=50,"Good",IF(Brushsheet[[#This Row],[Total]]>=45,"Fair",IF(Brushsheet[[#This Row],[Total]]>=40,"Pass","Weak"))))) -> Excellent
A3: 1 | B3: =CONCATENATE(_xlfn.XLOOKUP(Brushsheet[[#This Row],[Student ID]],Students!A:A,Students!E:E)," ",_xlfn.XLOOKUP(Brushsheet[[#This Row],[Student ID]],Students!A:A,Students!C:C)," ",_xlfn.XLOOKUP(Brushsheet[[#This Row],[Student ID]],Students!A:A,Students!D:D)) -> Ojo Josiah Muyiwa | C3: =_xlfn.XLOOKUP(Brushsheet[[#This Row],[Student ID]],Students!A:A,Students!J:J) -> JSS1 | D3: ENG001 | E3: =_xlfn.XLOOKUP(Brushsheet[[#This Row],[Subject ID]],Subjects!A:A,Subjects!B:B) -> English | F3: 1st | G3: 3 | H3: 12 | I3: 5 | J3: 48 | K3: =SUM(Brushsheet[[#This Row],[1st CA]:[Exam Score]]) -> 68 | L3: =IF(Brushsheet[[#This Row],[Total]]>=70,"A",IF(Brushsheet[[#This Row],[Total]]>=60,"B",IF(Brushsheet[[#This Row],[Total]]>=50,"C",IF(Brushsheet[[#This Row],[Total]]>=45,"D",IF(Brushsheet[[#This Row],[Total]]>=40,"E","F"))))) -> B | M3: =IF(Brushsheet[[#This Row],[Total]]>=70,"Excellent",IF(Brushsheet[[#This Row],[Total]]>=60,"V.Good",IF(Brushsheet[[#This Row],[Total]]>=50,"Good",IF(Brushsheet[[#This Row],[Total]]>=45,"Fair",IF(Brushsheet[[#This Row],[Total]]>=40,"Pass","Weak"))))) -> V.Good
A4: 1 | B4: =CONCATENATE(_xlfn.XLOOKUP(Brushsheet[[#This Row],[Student ID]],Students!A:A,Students!E:E)," ",_xlfn.XLOOKUP(Brushsheet[[#This Row],[Student ID]],Students!A:A,Students!C:C)," ",_xlfn.XLOOKUP(Brushsheet[[#This Row],[Student ID]],Students!A:A,Students!D:D)) -> Ojo Josiah Muyiwa | C4: =_xlfn.XLOOKUP(Brushsheet[[#This Row],[Student ID]],Students!A:A,Students!J:J) -> JSS1 | D4: SCI001 | E4: =_xlfn.XLOOKUP(Brushsheet[[#This Row],[Subject ID]],Subjects!A:A,Subjects!B:B) -> Science | F4: 1st | G4: 6 | H4: 8 | I4: 2 | J4: 36 | K4: =SUM(Brushsheet[[#This Row],[1st CA]:[Exam Score]]) -> 52 | L4: =IF(Brushsheet[[#This Row],[Total]]>=70,"A",IF(Brushsheet[[#This Row],[Total]]>=60,"B",IF(Brushsheet[[#This Row],[Total]]>=50,"C",IF(Brushsheet[[#This Row],[Total]]>=45,"D",IF(Brushsheet[[#This Row],[Total]]>=40,"E","F"))))) -> C | M4: =IF(Brushsheet[[#This Row],[Total]]>=70,"Excellent",IF(Brushsheet[[#This Row],[Total]]>=60,"V.Good",IF(Brushsheet[[#This Row],[Total]]>=50,"Good",IF(Brushsheet[[#This Row],[Total]]>=45,"Fair",IF(Brushsheet[[#This Row],[Total]]>=40,"Pass","Weak"))))) -> Good
A5: 1 | B5: =CONCATENATE(_xlfn.XLOOKUP(Brushsheet[[#This Row],[Student ID]],Students!A:A,Students!E:E)," ",_xlfn.XLOOKUP(Brushsheet[[#This Row],[Student ID]],Students!A:A,Students!C:C)," ",_xlfn.XLOOKUP(Brushsheet[[#This Row],[Student ID]],Students!A:A,Students!D:D)) -> Ojo Josiah Muyiwa | C5: =_xlfn.XLOOKUP(Brushsheet[[#This Row],[Student ID]],Students!A:A,Students!J:J) -> JSS1 | D5: COM001 | E5: =_xlfn.XLOOKUP(Brushsheet[[#This Row],[Subject ID]],Subjects!A:A,Subjects!B:B) -> Computer | F5: 1st | G5: 5 | H5: 8 | I5: 3 | J5: 25 | K5: =SUM(Brushsheet[[#This Row],[1st CA]:[Exam Score]]) -> 41 | L5: =IF(Brushsheet[[#This Row],[Total]]>=70,"A",IF(Brushsheet[[#This Row],[Total]]>=60,"B",IF(Brushsheet[[#This Row],[Total]]>=50,"C",IF(Brushsheet[[#This Row],[Total]]>=45,"D",IF(Brushsheet[[#This Row],[Total]]>=40,"E","F"))))) -> E | M5: =IF(Brushsheet[[#This Row],[Total]]>=70,"Excellent",IF(Brushsheet[[#This Row],[Total]]>=60,"V.Good",IF(Brushsheet[[#This Row],[Total]]>=50,"Good",IF(Brushsheet[[#This Row],[Total]]>=45,"Fair",IF(Brushsheet[[#This Row],[Total]]>=40,"Pass","Weak"))))) -> Pass
A6: 1 | B6: =CONCATENATE(_xlfn.XLOOKUP(Brushsheet[[#This Row],[Student ID]],Students!A:A,Students!E:E)," ",_xlfn.XLOOKUP(Brushsheet[[#This Row],[Student ID]],Students!A:A,Students!C:C)," ",_xlfn.XLOOKUP(Brushsheet[[#This Row],[Student ID]],Students!A:A,Students!D:D)) -> Ojo Josiah Muyiwa | C6: =_xlfn.XLOOKUP(Brushsheet[[#This Row],[Student ID]],Students!A:A,Students!J:J) -> JSS1 | D6: MUS001 | E6: =_xlfn.XLOOKUP(Brushsheet[[#This Row],[Subject ID]],Subjects!A:A,Subjects!B:B) -> Music | F6: 1st | G6: 15 | H6: 15 | I6: 10 | J6: 30 | K6: =SUM(Brushsheet[[#This Row],[1st CA]:[Exam Score]]) -> 70 | L6: =IF(Brushsheet[[#This Row],[Total]]>=70,"A",IF(Brushsheet[[#This Row],[Total]]>=60,"B",IF(Brushsheet[[#This Row],[Total]]>=50,"C",IF(Brushsheet[[#This Row],[Total]]>=45,"D",IF(Brushsheet[[#This Row],[Total]]>=40,"E","F"))))) -> A | M6: =IF(Brushsheet[[#This Row],[Total]]>=70,"Excellent",IF(Brushsheet[[#This Row],[Total]]>=60,"V.Good",IF(Brushsheet[[#This Row],[Total]]>=50,"Good",IF(Brushsheet[[#This Row],[Total]]>=45,"Fair",IF(Brushsheet[[#This Row],[Total]]>=40,"Pass","Weak"))))) -> Excellent
B7: =CONCATENATE(_xlfn.XLOOKUP(Brushsheet[[#This Row],[Student ID]],Students!A:A,Students!E:E)," ",_xlfn.XLOOKUP(Brushsheet[[#This Row],[Student ID]],Students!A:A,Students!C:C)," ",_xlfn.XLOOKUP(Brushsheet[[#This Row],[Student ID]],Students!A:A,Students!D:D)) | C7: =_xlfn.XLOOKUP(Brushsheet[[#This Row],[Student ID]],Students!A:A,Students!J:J) -> 0 | E7: =_xlfn.XLOOKUP(Brushsheet[[#This Row],[Subject ID]],Subjects!A:A,Subjects!B:B) -> 0 | K7: =SUM(Brushsheet[[#This Row],[1st CA]:[Exam Score]]) -> 0 | L7: =IF(Brushsheet[[#This Row],[Total]]>=70,"A",IF(Brushsheet[[#This Row],[Total]]>=60,"B",IF(Brushsheet[[#This Row],[Total]]>=50,"C",IF(Brushsheet[[#This Row],[Total]]>=45,"D",IF(Brushsheet[[#This Row],[Total]]>=40,"E","F"))))) -> F | M7: =IF(Brushsheet[[#This Row],[Total]]>=70,"Excellent",IF(Brushsheet[[#This Row],[Total]]>=60,"V.Good",IF(Brushsheet[[#This Row],[Total]]>=50,"Good",IF(Brushsheet[[#This Row],[Total]]>=45,"Fair",IF(Brushsheet[[#This Row],[Total]]>=40,"Pass","Weak"))))) -> Weak
B8: =CONCATENATE(_xlfn.XLOOKUP(Brushsheet[[#This Row],[Student ID]],Students!A:A,Students!E:E)," ",_xlfn.XLOOKUP(Brushsheet[[#This Row],[Student ID]],Students!A:A,Students!C:C)," ",_xlfn.XLOOKUP(Brushsheet[[#This Row],[Student ID]],Students!A:A,Students!D:D)) | C8: =_xlfn.XLOOKUP(Brushsheet[[#This Row],[Student ID]],Students!A:A,Students!J:J) -> 0 | E8: =_xlfn.XLOOKUP(Brushsheet[[#This Row],[Subject ID]],Subjects!A:A,Subjects!B:B) -> 0 | K8: =SUM(Brushsheet[[#This Row],[1st CA]:[Exam Score]]) -> 0 | L8: =IF(Brushsheet[[#This Row],[Total]]>=70,"A",IF(Brushsheet[[#This Row],[Total]]>=60,"B",IF(Brushsheet[[#This Row],[Total]]>=50,"C",IF(Brushsheet[[#This Row],[Total]]>=45,"D",IF(Brushsheet[[#This Row],[Total]]>=40,"E","F"))))) -> F | M8: =IF(Brushsheet[[#This Row],[Total]]>=70,"Excellent",IF(Brushsheet[[#This Row],[Total]]>=60,"V.Good",IF(Brushsheet[[#This Row],[Total]]>=50,"Good",IF(Brushsheet[[#This Row],[Total]]>=45,"Fair",IF(Brushsheet[[#This Row],[Total]]>=40,"Pass","Weak"))))) -> Weak
B9: =CONCATENATE(_xlfn.XLOOKUP(Brushsheet[[#This Row],[Student ID]],Students!A:A,Students!E:E)," ",_xlfn.XLOOKUP(Brushsheet[[#This Row],[Student ID]],Students!A:A,Students!C:C)," ",_xlfn.XLOOKUP(Brushsheet[[#This Row],[Student ID]],Students!A:A,Students!D:D)) | C9: =_xlfn.XLOOKUP(Brushsheet[[#This Row],[Student ID]],Students!A:A,Students!J:J) -> 0 | E9: =_xlfn.XLOOKUP(Brushsheet[[#This Row],[Subject ID]],Subjects!A:A,Subjects!B:B) -> 0 | K9: =SUM(Brushsheet[[#This Row],[1st CA]:[Exam Score]]) -> 0 | L9: =IF(Brushsheet[[#This Row],[Total]]>=70,"A",IF(Brushsheet[[#This Row],[Total]]>=60,"B",IF(Brushsheet[[#This Row],[Total]]>=50,"C",IF(Brushsheet[[#This Row],[Total]]>=45,"D",IF(Brushsheet[[#This Row],[Total]]>=40,"E","F"))))) -> F | M9: =IF(Brushsheet[[#This Row],[Total]]>=70,"Excellent",IF(Brushsheet[[#This Row],[Total]]>=60,"V.Good",IF(Brushsheet[[#This Row],[Total]]>=50,"Good",IF(Brushsheet[[#This Row],[Total]]>=45,"Fair",IF(Brushsheet[[#This Row],[Total]]>=40,"Pass","Weak"))))) -> Weak
B10: =CONCATENATE(_xlfn.XLOOKUP(Brushsheet[[#This Row],[Student ID]],Students!A:A,Students!E:E)," ",_xlfn.XLOOKUP(Brushsheet[[#This Row],[Student ID]],Students!A:A,Students!C:C)," ",_xlfn.XLOOKUP(Brushsheet[[#This Row],[Student ID]],Students!A:A,Students!D:D)) | C10: =_xlfn.XLOOKUP(Brushsheet[[#This Row],[Student ID]],Students!A:A,Students!J:J) -> 0 | E10: =_xlfn.XLOOKUP(Brushsheet[[#This Row],[Subject ID]],Subjects!A:A,Subjects!B:B) -> 0 | K10: =SUM(Brushsheet[[#This Row],[1st CA]:[Exam Score]]) -> 0 | L10: =IF(Brushsheet[[#This Row],[Total]]>=70,"A",IF(Brushsheet[[#This Row],[Total]]>=60,"B",IF(Brushsheet[[#This Row],[Total]]>=50,"C",IF(Brushsheet[[#This Row],[Total]]>=45,"D",IF(Brushsheet[[#This Row],[Total]]>=40,"E","F"))))) -> F | M10: =IF(Brushsheet[[#This Row],[Total]]>=70,"Excellent",IF(Brushsheet[[#This Row],[Total]]>=60,"V.Good",IF(Brushsheet[[#This Row],[Total]]>=50,"Good",IF(Brushsheet[[#This Row],[Total]]>=45,"Fair",IF(Brushsheet[[#This Row],[Total]]>=40,"Pass","Weak"))))) -> Weak
B11: =CONCATENATE(_xlfn.XLOOKUP(Brushsheet[[#This Row],[Student ID]],Students!A:A,Students!E:E)," ",_xlfn.XLOOKUP(Brushsheet[[#This Row],[Student ID]],Students!A:A,Students!C:C)," ",_xlfn.XLOOKUP(Brushsheet[[#This Row],[Student ID]],Students!A:A,Students!D:D)) | C11: =_xlfn.XLOOKUP(Brushsheet[[#This Row],[Student ID]],Students!A:A,Students!J:J) -> 0 | E11: =_xlfn.XLOOKUP(Brushsheet[[#This Row],[Subject ID]],Subjects!A:A,Subjects!B:B) -> 0 | K11: =SUM(Brushsheet[[#This Row],[1st CA]:[Exam Score]]) -> 0 | L11: =IF(Brushsheet[[#This Row],[Total]]>=70,"A",IF(Brushsheet[[#This Row],[Total]]>=60,"B",IF(Brushsheet[[#This Row],[Total]]>=50,"C",IF(Brushsheet[[#This Row],[Total]]>=45,"D",IF(Brushsheet[[#This Row],[Total]]>=40,"E","F"))))) -> F | M11: =IF(Brushsheet[[#This Row],[Total]]>=70,"Excellent",IF(Brushsheet[[#This Row],[Total]]>=60,"V.Good",IF(Brushsheet[[#This Row],[Total]]>=50,"Good",IF(Brushsheet[[#This Row],[Total]]>=45,"Fair",IF(Brushsheet[[#This Row],[Total]]>=40,"Pass","Weak"))))) -> Weak
B12: =CONCATENATE(_xlfn.XLOOKUP(Brushsheet[[#This Row],[Student ID]],Students!A:A,Students!E:E)," ",_xlfn.XLOOKUP(Brushsheet[[#This Row],[Student ID]],Students!A:A,Students!C:C)," ",_xlfn.XLOOKUP(Brushsheet[[#This Row],[Student ID]],Students!A:A,Students!D:D)) | C12: =_xlfn.XLOOKUP(Brushsheet[[#This Row],[Student ID]],Students!A:A,Students!J:J) -> 0 | E12: =_xlfn.XLOOKUP(Brushsheet[[#This Row],[Subject ID]],Subjects!A:A,Subjects!B:B) -> 0 | K12: =SUM(Brushsheet[[#This Row],[1st CA]:[Exam Score]]) -> 0 | L12: =IF(Brushsheet[[#This Row],[Total]]>=70,"A",IF(Brushsheet[[#This Row],[Total]]>=60,"B",IF(Brushsheet[[#This Row],[Total]]>=50,"C",IF(Brushsheet[[#This Row],[Total]]>=45,"D",IF(Brushsheet[[#This Row],[Total]]>=40,"E","F"))))) -> F | M12: =IF(Brushsheet[[#This Row],[Total]]>=70,"Excellent",IF(Brushsheet[[#This Row],[Total]]>=60,"V.Good",IF(Brushsheet[[#This Row],[Total]]>=50,"Good",IF(Brushsheet[[#This Row],[Total]]>=45,"Fair",IF(Brushsheet[[#This Row],[Total]]>=40,"Pass","Weak"))))) -> Weak
B13: =CONCATENATE(_xlfn.XLOOKUP(Brushsheet[[#This Row],[Student ID]],Students!A:A,Students!E:E)," ",_xlfn.XLOOKUP(Brushsheet[[#This Row],[Student ID]],Students!A:A,Students!C:C)," ",_xlfn.XLOOKUP(Brushsheet[[#This Row],[Student ID]],Students!A:A,Students!D:D)) | C13: =_xlfn.XLOOKUP(Brushsheet[[#This Row],[Student ID]],Students!A:A,Students!J:J) -> 0 | E13: =_xlfn.XLOOKUP(Brushsheet[[#This Row],[Subject ID]],Subjects!A:A,Subjects!B:B) -> 0 | K13: =SUM(Brushsheet[[#This Row],[1st CA]:[Exam Score]]) -> 0 | L13: =IF(Brushsheet[[#This Row],[Total]]>=70,"A",IF(Brushsheet[[#This Row],[Total]]>=60,"B",IF(Brushsheet[[#This Row],[Total]]>=50,"C",IF(Brushsheet[[#This Row],[Total]]>=45,"D",IF(Brushsheet[[#This Row],[Total]]>=40,"E","F"))))) -> F | M13: =IF(Brushsheet[[#This Row],[Total]]>=70,"Excellent",IF(Brushsheet[[#This Row],[Total]]>=60,"V.Good",IF(Brushsheet[[#This Row],[Total]]>=50,"Good",IF(Brushsheet[[#This Row],[Total]]>=45,"Fair",IF(Brushsheet[[#This Row],[Total]]>=40,"Pass","Weak"))))) -> Weak
B14: =CONCATENATE(_xlfn.XLOOKUP(Brushsheet[[#This Row],[Student ID]],Students!A:A,Students!E:E)," ",_xlfn.XLOOKUP(Brushsheet[[#This Row],[Student ID]],Students!A:A,Students!C:C)," ",_xlfn.XLOOKUP(Brushsheet[[#This Row],[Student ID]],Students!A:A,Students!D:D)) | C14: =_xlfn.XLOOKUP(Brushsheet[[#This Row],[Student ID]],Students!A:A,Students!J:J) -> 0 | E14: =_xlfn.XLOOKUP(Brushsheet[[#This Row],[Subject ID]],Subjects!A:A,Subjects!B:B) -> 0 | K14: =SUM(Brushsheet[[#This Row],[1st CA]:[Exam Score]]) -> 0 | L14: =IF(Brushsheet[[#This Row],[Total]]>=70,"A",IF(Brushsheet[[#This Row],[Total]]>=60,"B",IF(Brushsheet[[#This Row],[Total]]>=50,"C",IF(Brushsheet[[#This Row],[Total]]>=45,"D",IF(Brushsheet[[#This Row],[Total]]>=40,"E","F"))))) -> F | M14: =IF(Brushsheet[[#This Row],[Total]]>=70,"Excellent",IF(Brushsheet[[#This Row],[Total]]>=60,"V.Good",IF(Brushsheet[[#This Row],[Total]]>=50,"Good",IF(Brushsheet[[#This Row],[Total]]>=45,"Fair",IF(Brushsheet[[#This Row],[Total]]>=40,"Pass","Weak"))))) -> Weak
B15: =CONCATENATE(_xlfn.XLOOKUP(Brushsheet[[#This Row],[Student ID]],Students!A:A,Students!E:E)," ",_xlfn.XLOOKUP(Brushsheet[[#This Row],[Student ID]],Students!A:A,Students!C:C)," ",_xlfn.XLOOKUP(Brushsheet[[#This Row],[Student ID]],Students!A:A,Students!D:D)) | C15: =_xlfn.XLOOKUP(Brushsheet[[#This Row],[Student ID]],Students!A:A,Students!J:J) -> 0 | E15: =_xlfn.XLOOKUP(Brushsheet[[#This Row],[Subject ID]],Subjects!A:A,Subjects!B:B) -> 0 | K15: =SUM(Brushsheet[[#This Row],[1st CA]:[Exam Score]]) -> 0 | L15: =IF(Brushsheet[[#This Row],[Total]]>=70,"A",IF(Brushsheet[[#This Row],[Total]]>=60,"B",IF(Brushsheet[[#This Row],[Total]]>=50,"C",IF(Brushsheet[[#This Row],[Total]]>=45,"D",IF(Brushsheet[[#This Row],[Total]]>=40,"E","F"))))) -> F | M15: =IF(Brushsheet[[#This Row],[Total]]>=70,"Excellent",IF(Brushsheet[[#This Row],[Total]]>=60,"V.Good",IF(Brushsheet[[#This Row],[Total]]>=50,"Good",IF(Brushsheet[[#This Row],[Total]]>=45,"Fair",IF(Brushsheet[[#This Row],[Total]]>=40,"Pass","Weak"))))) -> Weak
B16: =CONCATENATE(_xlfn.XLOOKUP(Brushsheet[[#This Row],[Student ID]],Students!A:A,Students!E:E)," ",_xlfn.XLOOKUP(Brushsheet[[#This Row],[Student ID]],Students!A:A,Students!C:C)," ",_xlfn.XLOOKUP(Brushsheet[[#This Row],[Student ID]],Students!A:A,Students!D:D)) | C16: =_xlfn.XLOOKUP(Brushsheet[[#This Row],[Student ID]],Students!A:A,Students!J:J) -> 0 | E16: =_xlfn.XLOOKUP(Brushsheet[[#This Row],[Subject ID]],Subjects!A:A,Subjects!B:B) -> 0 | K16: =SUM(Brushsheet[[#This Row],[1st CA]:[Exam Score]]) -> 0 | L16: =IF(Brushsheet[[#This Row],[Total]]>=70,"A",IF(Brushsheet[[#This Row],[Total]]>=60,"B",IF(Brushsheet[[#This Row],[Total]]>=50,"C",IF(Brushsheet[[#This Row],[Total]]>=45,"D",IF(Brushsheet[[#This Row],[Total]]>=40,"E","F"))))) -> F | M16: =IF(Brushsheet[[#This Row],[Total]]>=70,"Excellent",IF(Brushsheet[[#This Row],[Total]]>=60,"V.Good",IF(Brushsheet[[#This Row],[Total]]>=50,"Good",IF(Brushsheet[[#This Row],[Total]]>=45,"Fair",IF(Brushsheet[[#This Row],[Total]]>=40,"Pass","Weak"))))) -> Weak
B17: =CONCATENATE(_xlfn.XLOOKUP(Brushsheet[[#This Row],[Student ID]],Students!A:A,Students!E:E)," ",_xlfn.XLOOKUP(Brushsheet[[#This Row],[Student ID]],Students!A:A,Students!C:C)," ",_xlfn.XLOOKUP(Brushsheet[[#This Row],[Student ID]],Students!A:A,Students!D:D)) | C17: =_xlfn.XLOOKUP(Brushsheet[[#This Row],[Student ID]],Students!A:A,Students!J:J) -> 0 | E17: =_xlfn.XLOOKUP(Brushsheet[[#This Row],[Subject ID]],Subjects!A:A,Subjects!B:B) -> 0 | K17: =SUM(Brushsheet[[#This Row],[1st CA]:[Exam Score]]) -> 0 | L17: =IF(Brushsheet[[#This Row],[Total]]>=70,"A",IF(Brushsheet[[#This Row],[Total]]>=60,"B",IF(Brushsheet[[#This Row],[Total]]>=50,"C",IF(Brushsheet[[#This Row],[Total]]>=45,"D",IF(Brushsheet[[#This Row],[Total]]>=40,"E","F"))))) -> F | M17: =IF(Brushsheet[[#This Row],[Total]]>=70,"Excellent",IF(Brushsheet[[#This Row],[Total]]>=60,"V.Good",IF(Brushsheet[[#This Row],[Total]]>=50,"Good",IF(Brushsheet[[#This Row],[Total]]>=45,"Fair",IF(Brushsheet[[#This Row],[Total]]>=40,"Pass","Weak"))))) -> Weak
B18: =CONCATENATE(_xlfn.XLOOKUP(Brushsheet[[#This Row],[Student ID]],Students!A:A,Students!E:E)," ",_xlfn.XLOOKUP(Brushsheet[[#This Row],[Student ID]],Students!A:A,Students!C:C)," ",_xlfn.XLOOKUP(Brushsheet[[#This Row],[Student ID]],Students!A:A,Students!D:D)) | C18: =_xlfn.XLOOKUP(Brushsheet[[#This Row],[Student ID]],Students!A:A,Students!J:J) -> 0 | E18: =_xlfn.XLOOKUP(Brushsheet[[#This Row],[Subject ID]],Subjects!A:A,Subjects!B:B) -> 0 | K18: =SUM(Brushsheet[[#This Row],[1st CA]:[Exam Score]]) -> 0 | L18: =IF(Brushsheet[[#This Row],[Total]]>=70,"A",IF(Brushsheet[[#This Row],[Total]]>=60,"B",IF(Brushsheet[[#This Row],[Total]]>=50,"C",IF(Brushsheet[[#This Row],[Total]]>=45,"D",IF(Brushsheet[[#This Row],[Total]]>=40,"E","F"))))) -> F | M18: =IF(Brushsheet[[#This Row],[Total]]>=70,"Excellent",IF(Brushsheet[[#This Row],[Total]]>=60,"V.Good",IF(Brushsheet[[#This Row],[Total]]>=50,"Good",IF(Brushsheet[[#This Row],[Total]]>=45,"Fair",IF(Brushsheet[[#This Row],[Total]]>=40,"Pass","Weak"))))) -> Weak
... B101: =CONCATENATE(_xlfn.XLOOKUP(Brushsheet[[#This Row],[Student ID]],Students!A:A,Students!E:E)," ",_xlfn.XLOOKUP(Brushsheet[[#This Row],[Student ID]],Students!A:A,Students!C:C)," ",_xlfn.XLOOKUP(Brushsheet[[#This Row],[Student ID]],Students!A:A,Students!D:D)) | C101: =_xlfn.XLOOKUP(Brushsheet[[#This Row],[Student ID]],Students!A:A,Students!J:J) -> 0 | E101: =_xlfn.XLOOKUP(Brushsheet[[#This Row],[Subject ID]],Subjects!A:A,Subjects!B:B) -> 0 | K101: =SUM(Brushsheet[[#This Row],[1st CA]:[Exam Score]]) -> 0 | L101: =IF(Brushsheet[[#This Row],[Total]]>=70,"A",IF(Brushsheet[[#This Row],[Total]]>=60,"B",IF(Brushsheet[[#This Row],[Total]]>=50,"C",IF(Brushsheet[[#This Row],[Total]]>=45,"D",IF(Brushsheet[[#This Row],[Total]]>=40,"E","F"))))) -> F | M101: =IF(Brushsheet[[#This Row],[Total]]>=70,"Excellent",IF(Brushsheet[[#This Row],[Total]]>=60,"V.Good",IF(Brushsheet[[#This Row],[Total]]>=50,"Good",IF(Brushsheet[[#This Row],[Total]]>=45,"Fair",IF(Brushsheet[[#This Row],[Total]]>=40,"Pass","Weak"))))) -> Weak

Sheet Results
B2: Student_ID | C2: Student_Name | D2: Term | E2: Session | F2: Class | G2: Gender
C3: =CONCATENATE((_xlfn.XLOOKUP(Table1[[#This Row],[Student_ID]],Students!A:A,Students!E:E))," ",(_xlfn.XLOOKUP(Table1[[#This Row],[Student_ID]],Students!A:A,Students!C:C))," ",(_xlfn.XLOOKUP(Table1[[#This Row],[Student_ID]],Students!A:A,Students!D:D))) | F3: =_xlfn.XLOOKUP(Table1[[#This Row],[Student_ID]],Students!A:A,Students!J:J) -> 0 | G3: =VLOOKUP(Table1[[#This Row],[Student_ID]],Students!A:F,6,FALSE) -> #N/A
B4: Subject_Name | C4: 1st_CA | D4: 2nd_CA | E4: Assignment | F4: Exam | G4: Total | H4: Grade | I4: Remark | J4: Class_Position
B5: {=IFERROR(INDEX(Brushsheet!E:E,SMALL(IF(Brushsheet!A:A=Table1[Student_ID],ROW(Brushsheet!A:A)),ROW(A1))),"")} -> 0 | C5: {=_xlfn.XLOOKUP(1,(Brushsheet!A:A=Table1[Student_ID])*(Brushsheet!E:E=Result[[#This Row],[Subject_Name]]),Brushsheet!G:G,"")} -> 0 | D5: {=_xlfn.XLOOKUP(1,(Brushsheet!A:A=Table1[Student_ID])*(Brushsheet!E:E=Result[[#This Row],[Subject_Name]]),Brushsheet!H:H,"")} -> 0 | E5: {=_xlfn.XLOOKUP(1,(Brushsheet!A:A=Table1[Student_ID])*(Brushsheet!E:E=Result[[#This Row],[Subject_Name]]),Brushsheet!I:I,"")} -> 0 | F5: {=_xlfn.XLOOKUP(1,(Brushsheet!A:A=Table1[Student_ID])*(Brushsheet!E:E=Result[[#This Row],[Subject_Name]]),Brushsheet!J:J,"")} -> 0 | G5: =SUM(C5:F5) -> 0 | H5: {=_xlfn.XLOOKUP(1,(Brushsheet!A:A=Table1[Student_ID])*(Brushsheet!E:E=Result[[#This Row],[Subject_Name]]),Brushsheet!L:L,"")} -> F | I5: {=_xlfn.XLOOKUP(1,(Brushsheet!A:A=Table1[Student_ID])*(Brushsheet!E:E=Result[[#This Row],[Subject_Name]]),Brushsheet!M:M,"")} -> Weak
B6: {=IFERROR(INDEX(Brushsheet!E:E,SMALL(IF(Brushsheet!A:A=Table1[Student_ID],ROW(Brushsheet!A:A)),ROW(A2))),"")} -> 0 | C6: {=_xlfn.XLOOKUP(1,(Brushsheet!A:A=Table1[Student_ID])*(Brushsheet!E:E=Result[[#This Row],[Subject_Name]]),Brushsheet!G:G,"")} -> 0 | D6: {=_xlfn.XLOOKUP(1,(Brushsheet!A:A=Table1[Student_ID])*(Brushsheet!E:E=Result[[#This Row],[Subject_Name]]),Brushsheet!H:H,"")} -> 0 | E6: {=_xlfn.XLOOKUP(1,(Brushsheet!A:A=Table1[Student_ID])*(Brushsheet!E:E=Result[[#This Row],[Subject_Name]]),Brushsheet!I:I,"")} -> 0 | F6: {=_xlfn.XLOOKUP(1,(Brushsheet!A:A=Table1[Student_ID])*(Brushsheet!E:E=Result[[#This Row],[Subject_Name]]),Brushsheet!J:J,"")} -> 0 | G6: =SUM(C6:F6) -> 0 | H6: {=_xlfn.XLOOKUP(1,(Brushsheet!A:A=Table1[Student_ID])*(Brushsheet!E:E=Result[[#This Row],[Subject_Name]]),Brushsheet!L:L,"")} -> F | I6: {=_xlfn.XLOOKUP(1,(Brushsheet!A:A=Table1[Student_ID])*(Brushsheet!E:E=Result[[#This Row],[Subject_Name]]),Brushsheet!M:M,"")} -> Weak
B7: {=IFERROR(INDEX(Brushsheet!E:E,SMALL(IF(Brushsheet!A:A=Table1[Student_ID],ROW(Brushsheet!A:A)),ROW(A3))),"")} -> 0 | C7: {=_xlfn.XLOOKUP(1,(Brushsheet!A:A=Table1[Student_ID])*(Brushsheet!E:E=Result[[#This Row],[Subject_Name]]),Brushsheet!G:G,"")} -> 0 | D7: {=_xlfn.XLOOKUP(1,(Brushsheet!A:A=Table1[Student_ID])*(Brushsheet!E:E=Result[[#This Row],[Subject_Name]]),Brushsheet!H:H,"")} -> 0 | E7: {=_xlfn.XLOOKUP(1,(Brushsheet!A:A=Table1[Student_ID])*(Brushsheet!E:E=Result[[#This Row],[Subject_Name]]),Brushsheet!I:I,"")} -> 0 | F7: {=_xlfn.XLOOKUP(1,(Brushsheet!A:A=Table1[Student_ID])*(Brushsheet!E:E=Result[[#This Row],[Subject_Name]]),Brushsheet!J:J,"")} -> 0 | G7: =SUM(C7:F7) -> 0 | H7: {=_xlfn.XLOOKUP(1,(Brushsheet!A:A=Table1[Student_ID])*(Brushsheet!E:E=Result[[#This Row],[Subject_Name]]),Brushsheet!L:L,"")} -> F | I7: {=_xlfn.XLOOKUP(1,(Brushsheet!A:A=Table1[Student_ID])*(Brushsheet!E:E=Result[[#This Row],[Subject_Name]]),Brushsheet!M:M,"")} -> Weak
B8: {=IFERROR(INDEX(Brushsheet!E:E,SMALL(IF(Brushsheet!A:A=Table1[Student_ID],ROW(Brushsheet!A:A)),ROW(A4))),"")} -> 0 | C8: {=_xlfn.XLOOKUP(1,(Brushsheet!A:A=Table1[Student_ID])*(Brushsheet!E:E=Result[[#This Row],[Subject_Name]]),Brushsheet!G:G,"")} -> 0 | D8: {=_xlfn.XLOOKUP(1,(Brushsheet!A:A=Table1[Student_ID])*(Brushsheet!E:E=Result[[#This Row],[Subject_Name]]),Brushsheet!H:H,"")} -> 0 | E8: {=_xlfn.XLOOKUP(1,(Brushsheet!A:A=Table1[Student_ID])*(Brushsheet!E:E=Result[[#This Row],[Subject_Name]]),Brushsheet!I:I,"")} -> 0 | F8: {=_xlfn.XLOOKUP(1,(Brushsheet!A:A=Table1[Student_ID])*(Brushsheet!E:E=Result[[#This Row],[Subject_Name]]),Brushsheet!J:J,"")} -> 0 | G8: =SUM(C8:F8) -> 0 | H8: {=_xlfn.XLOOKUP(1,(Brushsheet!A:A=Table1[Student_ID])*(Brushsheet!E:E=Result[[#This Row],[Subject_Name]]),Brushsheet!L:L,"")} -> F | I8: {=_xlfn.XLOOKUP(1,(Brushsheet!A:A=Table1[Student_ID])*(Brushsheet!E:E=Result[[#This Row],[Subject_Name]]),Brushsheet!M:M,"")} -> Weak
B9: {=IFERROR(INDEX(Brushsheet!E:E,SMALL(IF(Brushsheet!A:A=Table1[Student_ID],ROW(Brushsheet!A:A)),ROW(A5))),"")} -> 0 | C9: {=_xlfn.XLOOKUP(1,(Brushsheet!A:A=Table1[Student_ID])*(Brushsheet!E:E=Result[[#This Row],[Subject_Name]]),Brushsheet!G:G,"")} -> 0 | D9: {=_xlfn.XLOOKUP(1,(Brushsheet!A:A=Table1[Student_ID])*(Brushsheet!E:E=Result[[#This Row],[Subject_Name]]),Brushsheet!H:H,"")} -> 0 | E9: {=_xlfn.XLOOKUP(1,(Brushsheet!A:A=Table1[Student_ID])*(Brushsheet!E:E=Result[[#This Row],[Subject_Name]]),Brushsheet!I:I,"")} -> 0 | F9: {=_xlfn.XLOOKUP(1,(Brushsheet!A:A=Table1[Student_ID])*(Brushsheet!E:E=Result[[#This Row],[Subject_Name]]),Brushsheet!J:J,"")} -> 0 | G9: =SUM(C9:F9) -> 0 | H9: {=_xlfn.XLOOKUP(1,(Brushsheet!A:A=Table1[Student_ID])*(Brushsheet!E:E=Result[[#This Row],[Subject_Name]]),Brushsheet!L:L,"")} -> F | I9: {=_xlfn.XLOOKUP(1,(Brushsheet!A:A=Table1[Student_ID])*(Brushsheet!E:E=Result[[#This Row],[Subject_Name]]),Brushsheet!M:M,"")} -> Weak
B10: {=IFERROR(INDEX(Brushsheet!E:E,SMALL(IF(Brushsheet!A:A=Table1[Student_ID],ROW(Brushsheet!A:A)),ROW(A6))),"")} -> 0 | C10: {=_xlfn.XLOOKUP(1,(Brushsheet!A:A=Table1[Student_ID])*(Brushsheet!E:E=Result[[#This Row],[Subject_Name]]),Brushsheet!G:G,"")} -> 0 | D10: {=_xlfn.XLOOKUP(1,(Brushsheet!A:A=Table1[Student_ID])*(Brushsheet!E:E=Result[[#This Row],[Subject_Name]]),Brushsheet!H:H,"")} -> 0 | E10: {=_xlfn.XLOOKUP(1,(Brushsheet!A:A=Table1[Student_ID])*(Brushsheet!E:E=Result[[#This Row],[Subject_Name]]),Brushsheet!I:I,"")} -> 0 | F10: {=_xlfn.XLOOKUP(1,(Brushsheet!A:A=Table1[Student_ID])*(Brushsheet!E:E=Result[[#This Row],[Subject_Name]]),Brushsheet!J:J,"")} -> 0 | G10: =SUM(C10:F10) -> 0 | H10: {=_xlfn.XLOOKUP(1,(Brushsheet!A:A=Table1[Student_ID])*(Brushsheet!E:E=Result[[#This Row],[Subject_Name]]),Brushsheet!L:L,"")} -> F | I10: {=_xlfn.XLOOKUP(1,(Brushsheet!A:A=Table1[Student_ID])*(Brushsheet!E:E=Result[[#This Row],[Subject_Name]]),Brushsheet!M:M,"")} -> Weak
B11: {=IFERROR(INDEX(Brushsheet!E:E,SMALL(IF(Brushsheet!A:A=Table1[Student_ID],ROW(Brushsheet!A:A)),ROW(A7))),"")} -> 0 | C11: {=_xlfn.XLOOKUP(1,(Brushsheet!A:A=Table1[Student_ID])*(Brushsheet!E:E=Result[[#This Row],[Subject_Name]]),Brushsheet!G:G,"")} -> 0 | D11: {=_xlfn.XLOOKUP(1,(Brushsheet!A:A=Table1[Student_ID])*(Brushsheet!E:E=Result[[#This Row],[Subject_Name]]),Brushsheet!H:H,"")} -> 0 | E11: {=_xlfn.XLOOKUP(1,(Brushsheet!A:A=Table1[Student_ID])*(Brushsheet!E:E=Result[[#This Row],[Subject_Name]]),Brushsheet!I:I,"")} -> 0 | F11: {=_xlfn.XLOOKUP(1,(Brushsheet!A:A=Table1[Student_ID])*(Brushsheet!E:E=Result[[#This Row],[Subject_Name]]),Brushsheet!J:J,"")} -> 0 | G11: =SUM(C11:F11) -> 0 | H11: {=_xlfn.XLOOKUP(1,(Brushsheet!A:A=Table1[Student_ID])*(Brushsheet!E:E=Result[[#This Row],[Subject_Name]]),Brushsheet!L:L,"")} -> F | I11: {=_xlfn.XLOOKUP(1,(Brushsheet!A:A=Table1[Student_ID])*(Brushsheet!E:E=Result[[#This Row],[Subject_Name]]),Brushsheet!M:M,"")} -> Weak
B12: {=IFERROR(INDEX(Brushsheet!E:E,SMALL(IF(Brushsheet!A:A=Table1[Student_ID],ROW(Brushsheet!A:A)),ROW(A8))),"")} -> 0 | C12: {=_xlfn.XLOOKUP(1,(Brushsheet!A:A=Table1[Student_ID])*(Brushsheet!E:E=Result[[#This Row],[Subject_Name]]),Brushsheet!G:G,"")} -> 0 | D12: {=_xlfn.XLOOKUP(1,(Brushsheet!A:A=Table1[Student_ID])*(Brushsheet!E:E=Result[[#This Row],[Subject_Name]]),Brushsheet!H:H,"")} -> 0 | E12: {=_xlfn.XLOOKUP(1,(Brushsheet!A:A=Table1[Student_ID])*(Brushsheet!E:E=Result[[#This Row],[Subject_Name]]),Brushsheet!I:I,"")} -> 0 | F12: {=_xlfn.XLOOKUP(1,(Brushsheet!A:A=Table1[Student_ID])*(Brushsheet!E:E=Result[[#This Row],[Subject_Name]]),Brushsheet!J:J,"")} -> 0 | G12: =SUM(C12:F12) -> 0 | H12: {=_xlfn.XLOOKUP(1,(Brushsheet!A:A=Table1[Student_ID])*(Brushsheet!E:E=Result[[#This Row],[Subject_Name]]),Brushsheet!L:L,"")} -> F | I12: {=_xlfn.XLOOKUP(1,(Brushsheet!A:A=Table1[Student_ID])*(Brushsheet!E:E=Result[[#This Row],[Subject_Name]]),Brushsheet!M:M,"")} -> Weak
B13: {=IFERROR(INDEX(Brushsheet!E:E,SMALL(IF(Brushsheet!A:A=Table1[Student_ID],ROW(Brushsheet!A:A)),ROW(A9))),"")} -> 0 | C13: {=_xlfn.XLOOKUP(1,(Brushsheet!A:A=Table1[Student_ID])*(Brushsheet!E:E=Result[[#This Row],[Subject_Name]]),Brushsheet!G:G,"")} -> 0 | D13: {=_xlfn.XLOOKUP(1,(Brushsheet!A:A=Table1[Student_ID])*(Brushsheet!E:E=Result[[#This Row],[Subject_Name]]),Brushsheet!H:H,"")} -> 0 | E13: {=_xlfn.XLOOKUP(1,(Brushsheet!A:A=Table1[Student_ID])*(Brushsheet!E:E=Result[[#This Row],[Subject_Name]]),Brushsheet!I:I,"")} -> 0 | F13: {=_xlfn.XLOOKUP(1,(Brushsheet!A:A=Table1[Student_ID])*(Brushsheet!E:E=Result[[#This Row],[Subject_Name]]),Brushsheet!J:J,"")} -> 0 | G13: =SUM(C13:F13) -> 0 | H13: {=_xlfn.XLOOKUP(1,(Brushsheet!A:A=Table1[Student_ID])*(Brushsheet!E:E=Result[[#This Row],[Subject_Name]]),Brushsheet!L:L,"")} -> F | I13: {=_xlfn.XLOOKUP(1,(Brushsheet!A:A=Table1[Student_ID])*(Brushsheet!E:E=Result[[#This Row],[Subject_Name]]),Brushsheet!M:M,"")} -> Weak
B14: {=IFERROR(INDEX(Brushsheet!E:E,SMALL(IF(Brushsheet!A:A=Table1[Student_ID],ROW(Brushsheet!A:A)),ROW(A10))),"")} -> 0 | C14: {=_xlfn.XLOOKUP(1,(Brushsheet!A:A=Table1[Student_ID])*(Brushsheet!E:E=Result[[#This Row],[Subject_Name]]),Brushsheet!G:G,"")} -> 0 | D14: {=_xlfn.XLOOKUP(1,(Brushsheet!A:A=Table1[Student_ID])*(Brushsheet!E:E=Result[[#This Row],[Subject_Name]]),Brushsheet!H:H,"")} -> 0 | E14: {=_xlfn.XLOOKUP(1,(Brushsheet!A:A=Table1[Student_ID])*(Brushsheet!E:E=Result[[#This Row],[Subject_Name]]),Brushsheet!I:I,"")} -> 0 | F14: {=_xlfn.XLOOKUP(1,(Brushsheet!A:A=Table1[Student_ID])*(Brushsheet!E:E=Result[[#This Row],[Subject_Name]]),Brushsheet!J:J,"")} -> 0 | G14: =SUM(C14:F14) -> 0 | H14: {=_xlfn.XLOOKUP(1,(Brushsheet!A:A=Table1[Student_ID])*(Brushsheet!E:E=Result[[#This Row],[Subject_Name]]),Brushsheet!L:L,"")} -> F | I14: {=_xlfn.XLOOKUP(1,(Brushsheet!A:A=Table1[Student_ID])*(Brushsheet!E:E=Result[[#This Row],[Subject_Name]]),Brushsheet!M:M,"")} -> Weak
B15: {=IFERROR(INDEX(Brushsheet!E:E,SMALL(IF(Brushsheet!A:A=Table1[Student_ID],ROW(Brushsheet!A:A)),ROW(A11))),"")} -> 0 | C15: {=_xlfn.XLOOKUP(1,(Brushsheet!A:A=Table1[Student_ID])*(Brushsheet!E:E=Result[[#This Row],[Subject_Name]]),Brushsheet!G:G,"")} -> 0 | D15: {=_xlfn.XLOOKUP(1,(Brushsheet!A:A=Table1[Student_ID])*(Brushsheet!E:E=Result[[#This Row],[Subject_Name]]),Brushsheet!H:H,"")} -> 0 | E15: {=_xlfn.XLOOKUP(1,(Brushsheet!A:A=Table1[Student_ID])*(Brushsheet!E:E=Result[[#This Row],[Subject_Name]]),Brushsheet!I:I,"")} -> 0 | F15: {=_xlfn.XLOOKUP(1,(Brushsheet!A:A=Table1[Student_ID])*(Brushsheet!E:E=Result[[#This Row],[Subject_Name]]),Brushsheet!J:J,"")} -> 0 | G15: =SUM(C15:F15) -> 0 | H15: {=_xlfn.XLOOKUP(1,(Brushsheet!A:A=Table1[Student_ID])*(Brushsheet!E:E=Result[[#This Row],[Subject_Name]]),Brushsheet!L:L,"")} -> F | I15: {=_xlfn.XLOOKUP(1,(Brushsheet!A:A=Table1[Student_ID])*(Brushsheet!E:E=Result[[#This Row],[Subject_Name]]),Brushsheet!M:M,"")} -> Weak
B16: {=IFERROR(INDEX(Brushsheet!E:E,SMALL(IF(Brushsheet!A:A=Table1[Student_ID],ROW(Brushsheet!A:A)),ROW(A12))),"")} -> 0 | C16: {=_xlfn.XLOOKUP(1,(Brushsheet!A:A=Table1[Student_ID])*(Brushsheet!E:E=Result[[#This Row],[Subject_Name]]),Brushsheet!G:G,"")} -> 0 | D16: {=_xlfn.XLOOKUP(1,(Brushsheet!A:A=Table1[Student_ID])*(Brushsheet!E:E=Result[[#This Row],[Subject_Name]]),Brushsheet!H:H,"")} -> 0 | E16: {=_xlfn.XLOOKUP(1,(Brushsheet!A:A=Table1[Student_ID])*(Brushsheet!E:E=Result[[#This Row],[Subject_Name]]),Brushsheet!I:I,"")} -> 0 | F16: {=_xlfn.XLOOKUP(1,(Brushsheet!A:A=Table1[Student_ID])*(Brushsheet!E:E=Result[[#This Row],[Subject_Name]]),Brushsheet!J:J,"")} -> 0 | G16: =SUM(C16:F16) -> 0 | H16: {=_xlfn.XLOOKUP(1,(Brushsheet!A:A=Table1[Student_ID])*(Brushsheet!E:E=Result[[#This Row],[Subject_Name]]),Brushsheet!L:L,"")} -> F | I16: {=_xlfn.XLOOKUP(1,(Brushsheet!A:A=Table1[Student_ID])*(Brushsheet!E:E=Result[[#This Row],[Subject_Name]]),Brushsheet!M:M,"")} -> Weak
... B24: {=IFERROR(INDEX(Brushsheet!E:E,SMALL(IF(Brushsheet!A:A=Table1[Student_ID],ROW(Brushsheet!A:A)),ROW(A20))),"")} -> 0 | C24: {=_xlfn.XLOOKUP(1,(Brushsheet!A:A=Table1[Student_ID])*(Brushsheet!E:E=Result[[#This Row],[Subject_Name]]),Brushsheet!G:G,"")} -> 0 | D24: {=_xlfn.XLOOKUP(1,(Brushsheet!A:A=Table1[Student_ID])*(Brushsheet!E:E=Result[[#This Row],[Subject_Name]]),Brushsheet!H:H,"")} -> 0 | E24: {=_xlfn.XLOOKUP(1,(Brushsheet!A:A=Table1[Student_ID])*(Brushsheet!E:E=Result[[#This Row],[Subject_Name]]),Brushsheet!I:I,"")} -> 0 | F24: {=_xlfn.XLOOKUP(1,(Brushsheet!A:A=Table1[Student_ID])*(Brushsheet!E:E=Result[[#This Row],[Subject_Name]]),Brushsheet!J:J,"")} -> 0 | G24: =SUM(C24:F24) -> 0 | H24: {=_xlfn.XLOOKUP(1,(Brushsheet!A:A=Table1[Student_ID])*(Brushsheet!E:E=Result[[#This Row],[Subject_Name]]),Brushsheet!L:L,"")} -> F | I24: {=_xlfn.XLOOKUP(1,(Brushsheet!A:A=Table1[Student_ID])*(Brushsheet!E:E=Result[[#This Row],[Subject_Name]]),Brushsheet!M:M,"")} -> Weak
B25: Total | C25: =SUBTOTAL(109,Result[1st_CA]) -> 0 | D25: =SUBTOTAL(109,Result[2nd_CA]) -> 0 | E25: =SUBTOTAL(109,Result[Assignment]) -> 0 | F25: =SUBTOTAL(109,Result[Exam]) -> 0 | G25: =SUBTOTAL(109,Result[Total]) -> 0

Sheet Results Dashboard
A1: Student Name | B1: {=Table1[Student_Name]}
A15: Sum of Total | B15: Column Labels | I15: Row Labels | J15: Sum of 1st_CA | K15: Sum of 2nd_CA | L15: Sum of Assignment | N15: Sum of Exam | O15: Column Labels
A16: Row Labels | C16: A | D16: B | E16: C | F16: E | G16: Grand Total | J16: 0 | K16: 0 | L16: 0 | N16: Row Labels | P16: A | Q16: B | R16: C | S16: E | T16: Grand Total
B17: 0 | G17: 0 | I17: English | J17: 3 | K17: 12 | L17: 5 | O17: 0 | T17: 0
A18: English | D18: 68 | G18: 68 | I18: Mathematics | J18: 12 | K18: 13 | L18: 8 | N18: English | Q18: 48 | T18: 48
A19: Mathematics | C19: 86 | G19: 86 | I19: Science | J19: 6 | K19: 8 | L19: 2 | N19: Mathematics | P19: 53 | T19: 53
A20: Science | E20: 52 | G20: 52 | I20: Computer | J20: 5 | K20: 8 | L20: 3 | N20: Science | R20: 36 | T20: 36
A21: Computer | F21: 41 | G21: 41 | I21: Music | J21: 15 | K21: 15 | L21: 10 | N21: Computer | S21: 25 | T21: 25
A22: Music | C22: 70 | G22: 70 | I22: Grand Total | J22: 41 | K22: 56 | L22: 28 | N22: Music | P22: 30 | T22: 30
A23: Grand Total | B23: 0 | C23: 156 | D23: 68 | E23: 52 | F23: 41 | G23: 317 | N23: Grand Total | O23: 0 | P23: 83 | Q23: 48 | R23: 36 | S23: 25 | T23: 192

Sheet Attendance
A1: Student_ID | B1: Class | C1: Date | D1: Day | E1: Status | F1: Reason_for_Absence

Sheet Fees
A1: Student_ID | B1: Student Name | C1: Session | D1: Term | E1: Fee_Type | F1: Amount_Expected | G1: Amount_Paid | H1: Payment_Date | I1: Payment_Method | J1: Reciept_Number | K1: Fee Status | L1: Balance
A2: 1 | B2: =CONCATENATE((VLOOKUP(Fees[[#This Row],[Student_ID]],Students!A:E,5,FALSE))," ", (VLOOKUP(Fees[[#This Row],[Student_ID]],Students!A:F,3,FALSE))," ", (VLOOKUP(Fees[[#This Row],[Student_ID]],Students!A:E,4,FALSE))) -> Ojo Josiah Muyiwa | C2: 2025/2026 | D2: 1st | E2: Tuition | F2: 100000 | G2: 80000 | H2: 45820 | I2: Transfer | J2: 76 | K2: =IF(H2=0,"Paid","Outstanding") -> Outstanding | L2: =F2-G2 -> 20000
B3: =CONCATENATE((VLOOKUP(Fees[[#This Row],[Student_ID]],Students!A:E,5,FALSE))," ", (VLOOKUP(Fees[[#This Row],[Student_ID]],Students!A:F,3,FALSE))," ", (VLOOKUP(Fees[[#This Row],[Student_ID]],Students!A:E,4,FALSE))) -> #N/A | K3: =IF(H3=0,"Paid","Outstanding") -> Paid | L3: =F3-G3 -> 0
B4: =CONCATENATE((VLOOKUP(Fees[[#This Row],[Student_ID]],Students!A:E,5,FALSE))," ", (VLOOKUP(Fees[[#This Row],[Student_ID]],Students!A:F,3,FALSE))," ", (VLOOKUP(Fees[[#This Row],[Student_ID]],Students!A:E,4,FALSE))) -> #N/A | K4: =IF(H4=0,"Paid","Outstanding") -> Paid | L4: =F4-G4 -> 0
B5: =CONCATENATE((VLOOKUP(Fees[[#This Row],[Student_ID]],Students!A:E,5,FALSE))," ", (VLOOKUP(Fees[[#This Row],[Student_ID]],Students!A:F,3,FALSE))," ", (VLOOKUP(Fees[[#This Row],[Student_ID]],Students!A:E,4,FALSE))) -> #N/A | K5: =IF(H5=0,"Paid","Outstanding") -> Paid | L5: =F5-G5 -> 0
B6: =CONCATENATE((VLOOKUP(Fees[[#This Row],[Student_ID]],Students!A:E,5,FALSE))," ", (VLOOKUP(Fees[[#This Row],[Student_ID]],Students!A:F,3,FALSE))," ", (VLOOKUP(Fees[[#This Row],[Student_ID]],Students!A:E,4,FALSE))) -> #N/A | K6: =IF(H6=0,"Paid","Outstanding") -> Paid | L6: =F6-G6 -> 0
B7: =CONCATENATE((VLOOKUP(Fees[[#This Row],[Student_ID]],Students!A:E,5,FALSE))," ", (VLOOKUP(Fees[[#This Row],[Student_ID]],Students!A:F,3,FALSE))," ", (VLOOKUP(Fees[[#This Row],[Student_ID]],Students!A:E,4,FALSE))) -> #N/A | K7: =IF(H7=0,"Paid","Outstanding") -> Paid | L7: =F7-G7 -> 0
B8: =CONCATENATE((VLOOKUP(Fees[[#This Row],[Student_ID]],Students!A:E,5,FALSE))," ", (VLOOKUP(Fees[[#This Row],[Student_ID]],Students!A:F,3,FALSE))," ", (VLOOKUP(Fees[[#This Row],[Student_ID]],Students!A:E,4,FALSE))) -> #N/A | K8: =IF(H8=0,"Paid","Outstanding") -> Paid | L8: =F8-G8 -> 0
B9: =CONCATENATE((VLOOKUP(Fees[[#This Row],[Student_ID]],Students!A:E,5,FALSE))," ", (VLOOKUP(Fees[[#This Row],[Student_ID]],Students!A:F,3,FALSE))," ", (VLOOKUP(Fees[[#This Row],[Student_ID]],Students!A:E,4,FALSE))) -> #N/A | K9: =IF(H9=0,"Paid","Outstanding") -> Paid | L9: =F9-G9 -> 0
B10: =CONCATENATE((VLOOKUP(Fees[[#This Row],[Student_ID]],Students!A:E,5,FALSE))," ", (VLOOKUP(Fees[[#This Row],[Student_ID]],Students!A:F,3,FALSE))," ", (VLOOKUP(Fees[[#This Row],[Student_ID]],Students!A:E,4,FALSE))) -> #N/A | K10: =IF(H10=0,"Paid","Outstanding") -> Paid | L10: =F10-G10 -> 0
B11: =CONCATENATE((VLOOKUP(Fees[[#This Row],[Student_ID]],Students!A:E,5,FALSE))," ", (VLOOKUP(Fees[[#This Row],[Student_ID]],Students!A:F,3,FALSE))," ", (VLOOKUP(Fees[[#This Row],[Student_ID]],Students!A:E,4,FALSE))) -> #N/A | K11: =IF(H11=0,"Paid","Outstanding") -> Paid | L11: =F11-G11 -> 0
B12: =CONCATENATE((VLOOKUP(Fees[[#This Row],[Student_ID]],Students!A:E,5,FALSE))," ", (VLOOKUP(Fees[[#This Row],[Student_ID]],Students!A:F,3,FALSE))," ", (VLOOKUP(Fees[[#This Row],[Student_ID]],Students!A:E,4,FALSE))) -> #N/A | K12: =IF(H12=0,"Paid","Outstanding") -> Paid | L12: =F12-G12 -> 0
B13: =CONCATENATE((VLOOKUP(Fees[[#This Row],[Student_ID]],Students!A:E,5,FALSE))," ", (VLOOKUP(Fees[[#This Row],[Student_ID]],Students!A:F,3,FALSE))," ", (VLOOKUP(Fees[[#This Row],[Student_ID]],Students!A:E,4,FALSE))) -> #N/A | K13: =IF(H13=0,"Paid","Outstanding") -> Paid | L13: =F13-G13 -> 0
B14: =CONCATENATE((VLOOKUP(Fees[[#This Row],[Student_ID]],Students!A:E,5,FALSE))," ", (VLOOKUP(Fees[[#This Row],[Student_ID]],Students!A:F,3,FALSE))," ", (VLOOKUP(Fees[[#This Row],[Student_ID]],Students!A:E,4,FALSE))) -> #N/A | K14: =IF(H14=0,"Paid","Outstanding") -> Paid | L14: =F14-G14 -> 0
... B101: =CONCATENATE((VLOOKUP(Fees[[#This Row],[Student_ID]],Students!A:E,5,FALSE))," ", (VLOOKUP(Fees[[#This Row],[Student_ID]],Students!A:F,3,FALSE))," ", (VLOOKUP(Fees[[#This Row],[Student_ID]],Students!A:E,4,FALSE))) -> #N/A | K101: =IF(H101=0,"Paid","Outstanding") -> Paid | L101: =F101-G101 -> 0

Sheet Discipline
A1: Student_ID | B1: Date | C1: Incident_Type | D1: Description | E1: Action_Taken | F1: Reported_By

Sheet Inventory
A1: Item ID | B1: Item Name | C1: Category | D1: Quantity In | E1: Quantity Out | F1: Quantity Balance | G1: Unit Price | H1: Purchase Cost | I1: Location | J1: Reorder Level | K1: Stock status | L1: Last Updated
A2: CHM101 | B2: Hydrogen Peroxide(1M) | C2: Chemical | D2: 10 | E2: 3 | F2: =Table3[[#This Row],[Quantity In]]-Table3[[#This Row],[Quantity Out]] -> 7 | G2: 5000 | H2: =Table3[[#This Row],[Quantity In]]*Table3[[#This Row],[Unit Price]] -> 50000 | I2: Lab | J2: 5 | K2: =IF(Table3[[#This Row],[Quantity Balance]]<=Table3[[#This Row],[Reorder Level]],"Reorder!","OK") -> OK | L2: =TODAY() -> 46018
F3: =Table3[[#This Row],[Quantity In]]-Table3[[#This Row],[Quantity Out]] -> 0 | H3: =Table3[[#This Row],[Quantity In]]*Table3[[#This Row],[Unit Price]] -> 0 | K3: =IF(Table3[[#This Row],[Quantity Balance]]<=Table3[[#This Row],[Reorder Level]],"Reorder!","OK") -> Reorder! | L3: =TODAY() -> 46018
F4: =Table3[[#This Row],[Quantity In]]-Table3[[#This Row],[Quantity Out]] -> 0 | H4: =Table3[[#This Row],[Quantity In]]*Table3[[#This Row],[Unit Price]] -> 0 | K4: =IF(Table3[[#This Row],[Quantity Balance]]<=Table3[[#This Row],[Reorder Level]],"Reorder!","OK") -> Reorder! | L4: =TODAY() -> 46018
F5: =Table3[[#This Row],[Quantity In]]-Table3[[#This Row],[Quantity Out]] -> 0 | H5: =Table3[[#This Row],[Quantity In]]*Table3[[#This Row],[Unit Price]] -> 0 | K5: =IF(Table3[[#This Row],[Quantity Balance]]<=Table3[[#This Row],[Reorder Level]],"Reorder!","OK") -> Reorder! | L5: =TODAY() -> 46018
F6: =Table3[[#This Row],[Quantity In]]-Table3[[#This Row],[Quantity Out]] -> 0 | H6: =Table3[[#This Row],[Quantity In]]*Table3[[#This Row],[Unit Price]] -> 0 | K6: =IF(Table3[[#This Row],[Quantity Balance]]<=Table3[[#This Row],[Reorder Level]],"Reorder!","OK") -> Reorder! | L6: =TODAY() -> 46018
F7: =Table3[[#This Row],[Quantity In]]-Table3[[#This Row],[Quantity Out]] -> 0 | H7: =Table3[[#This Row],[Quantity In]]*Table3[[#This Row],[Unit Price]] -> 0 | K7: =IF(Table3[[#This Row],[Quantity Balance]]<=Table3[[#This Row],[Reorder Level]],"Reorder!","OK") -> Reorder! | L7: =TODAY() -> 46018
F8: =Table3[[#This Row],[Quantity In]]-Table3[[#This Row],[Quantity Out]] -> 0 | H8: =Table3[[#This Row],[Quantity In]]*Table3[[#This Row],[Unit Price]] -> 0 | K8: =IF(Table3[[#This Row],[Quantity Balance]]<=Table3[[#This Row],[Reorder Level]],"Reorder!","OK") -> Reorder! | L8: =TODAY() -> 46018
F9: =Table3[[#This Row],[Quantity In]]-Table3[[#This Row],[Quantity Out]] -> 0 | H9: =Table3[[#This Row],[Quantity In]]*Table3[[#This Row],[Unit Price]] -> 0 | K9: =IF(Table3[[#This Row],[Quantity Balance]]<=Table3[[#This Row],[Reorder Level]],"Reorder!","OK") -> Reorder! | L9: =TODAY() -> 46018
F10: =Table3[[#This Row],[Quantity In]]-Table3[[#This Row],[Quantity Out]] -> 0 | H10: =Table3[[#This Row],[Quantity In]]*Table3[[#This Row],[Unit Price]] -> 0 | K10: =IF(Table3[[#This Row],[Quantity Balance]]<=Table3[[#This Row],[Reorder Level]],"Reorder!","OK") -> Reorder! | L10: =TODAY() -> 46018
F11: =Table3[[#This Row],[Quantity In]]-Table3[[#This Row],[Quantity Out]] -> 0 | H11: =Table3[[#This Row],[Quantity In]]*Table3[[#This Row],[Unit Price]] -> 0 | K11: =IF(Table3[[#This Row],[Quantity Balance]]<=Table3[[#This Row],[Reorder Level]],"Reorder!","OK") -> Reorder! | L11: =TODAY() -> 46018
F12: =Table3[[#This Row],[Quantity In]]-Table3[[#This Row],[Quantity Out]] -> 0 | H12: =Table3[[#This Row],[Quantity In]]*Table3[[#This Row],[Unit Price]] -> 0 | K12: =IF(Table3[[#This Row],[Quantity Balance]]<=Table3[[#This Row],[Reorder Level]],"Reorder!","OK") -> Reorder! | L12: =TODAY() -> 46018
F13: =Table3[[#This Row],[Quantity In]]-Table3[[#This Row],[Quantity Out]] -> 0 | H13: =Table3[[#This Row],[Quantity In]]*Table3[[#This Row],[Unit Price]] -> 0 | K13: =IF(Table3[[#This Row],[Quantity Balance]]<=Table3[[#This Row],[Reorder Level]],"Reorder!","OK") -> Reorder! | L13: =TODAY() -> 46018
F14: =Table3[[#This Row],[Quantity In]]-Table3[[#This Row],[Quantity Out]] -> 0 | H14: =Table3[[#This Row],[Quantity In]]*Table3[[#This Row],[Unit Price]] -> 0 | K14: =IF(Table3[[#This Row],[Quantity Balance]]<=Table3[[#This Row],[Reorder Level]],"Reorder!","OK") -> Reorder! | L14: =TODAY() -> 46018
... F101: =Table3[[#This Row],[Quantity In]]-Table3[[#This Row],[Quantity Out]] -> 0 | H101: =Table3[[#This Row],[Quantity In]]*Table3[[#This Row],[Unit Price]] -> 0 | K101: =IF(Table3[[#This Row],[Quantity Balance]]<=Table3[[#This Row],[Reorder Level]],"Reorder!","OK") -> Reorder! | L101: =TODAY() -> 46018

Sheet Club Activities
A1: CLUB ACTIVITIES
A2: WEEKS | B2: POEM | C2: INSTRUCTOR | D2: QUIZES | E2: COORDINATOR | F2: SPELLING BEE | G2: HOST | H2: MORAL TALKS | I2: SPEAKER | J2: JET CLUB AGENDA | K2: PRESS CLUB AGENDA | L2: ART CLUB AGENDA
A3: 2
A4: 3
A5: 4 | H5: Why is it good to be punctual? | J5: 3D Shapes
A6: 5 | H6: Does it pay to be honest? | J6: Verdict Maths | K6: Oratoring Techniques | L6: Origamis
A7: 6 | H7: The importance of studying | J7: Boat Construction | K7: Current News Report | L7: WaterColor Painting
A8: 7 | H8: Avoiding bad entertainment | J8: Documentary Videos | K8: Interviews | L8: Cardboard Designs
A9: 8 | F9: Sporting Equipments | H9: Why should you do your homework? | J9: Car construction | K9: Debate | L9: Drama
A10: 9 | F10: Financial Terminologies | H10: What does it mean to be humble? | J10: House construction
A11: 10 | F11: Fashion Registers | H11: Is it boring to be polite and serious? | J11: Wind Alternator
J12: Aqueous Electrolysis

Sheet Time table
A1: TIME TABLE
A2: DAYS | B2: CLASS | C2: 0.33333333 | D2: 0.34722222 | E2: 0.375 | F2: 0.40277778 | G2: 0.43055556 | H2: 0.45833333 | I2: 0.47916667 | J2: 0.50694444 | K2: 0.53472222 | L2: 0.0625 | M2: 0.090277778 | N2: 0.125
A3: MONDAY | B3: JSS1 | C3: ASSEMBLY | D3: Maths | E3: S.Stu | F3: Eng | G3: B.Stu | H3: BREAK | I3: C.Sci | J3: Yor | K3: STUDY | L3: C.Sci Practical | M3: Lesson | N3: CLOSING TIME
B4: JSS2 | D4: Mor | E4: Maths | F4: B.Stu | G4: Eng | I4: Yor | J4: B.Stu | K4: C.Sci
B5: JSS3 | D5: S.Edu | E5: B.Stu | F5: Maths | G5: S.Stu | I5: STUDY | J5: C.Sci | K5: B.Stu
A6: TUESDAY | B6: JSS1 | D6: Hist | E6: H.Eco | F6: CCA | G6: B.Sci | I6: Eng | J6: Yor | K6: B.Stu | L6: A.Sci
B7: JSS2 | D7: CCA | E7: Hist | F7: B.Sci | G7: H.Eco | I7: S.Stu | J7: Eng | K7: A.Sci | L7: H.Edu
B8: JSS3 | D8: H.Eco | E8: B.Sci | F8: Hist | G8: CCA | I8: Yor | J8: A.Sci | K8: Eng | L8: S.Stu
A9: WEDNESDAY | B9: JSS1 | D9: SPORT | E9: C.Edu | F9: Eng | G9: Maths | I9: B.Tech | J9: S.Stu | K9: S.Edu | L9: Eng
B10: JSS2 | E10: Eng | F10: Maths | G10: S.Stu | I10: S.Edu | J10: B.Tech | K10: Eng | L10: CRS
B11: JSS3 | E11: Maths | F11: C.Edu | G11: Eng | I11: Hist | J11: Eng | K11: B.Tech | L11: C.Sci
A12: THURSDAY | B12: JSS1 | D12: CCA | E12: Eng | F12: C.Sci | G12: C.Edu | I12: H.Eco | J12: B.Tech | K12: S.Edu | L12: B.Sci
B13: JSS2 | D13: C.Edu | E13: CCA | F13: Eng | G13: Maths | I13: Yor | J13: B.Sci | K13: B.Tech | L13: H.Eco
B14: JSS3 | D14: Eng | E14: C.Edu | F14: CCA | G14: H.Eco | I14: B.Tech | J14: Eng | K14: B.Sci | L14: H.Edu
A15: FRIDAY | B15: TIME | D15: 0.34722222 | E15: 0.36805556 | F15: 0.38888889 | G15: 0.40972222 | H15: 0.43055556 | I15: 0.45138889 | J15: 0.47222222 | K15: 0.49305556 | L15: 0.51388889 | M15: 0.53472222 | N15: 0.041666667
B16: JSS1 | D16: CRS | E16: S.Edu | F16: Maths | G16: A.Sci | H16: H.Edu | I16: BREAK | J16: Eng | K16: Hist | L16: S.Stu | M16: Debate | N16: CLOSING TIME
B17: JSS2 | D17: H.Edu | E17: CRS | F17: A.Sci | G17: Maths | H17: C.Sci | J17: Hist | K17: Eng | L17: C.Edu
B18: JSS3 | D18: Maths | E18: A.Sci | F18: Yor | G18: H.Edu | H18: Hist | J18: S.Stu | K18: S.Edu | L18: CRS
A23: JSS 1-3 TEST TIMETABLE
A24: Days | B24: 8-9 | C24: 9-10 | D24: 10-11 | E24: 11-12 | F24: 12-1 | G24: 1-2
A25: Monday | B25: Maths | C25: Computer | D25: Agric | E25: Break
A26: Tuesday
A27: Wednesday | B27: History | C27: Social Stu. | D27: Basic Sci. | F27: Security Edu. | G27: Morals
A28: Thursday | B28: Health Edu. | C28: Civic | D28: English | F28: B.Tech | G28: CRS
A29: Friday | B29: CCA | C29: Business Stu. | D29: Home-Eco | F29: Yoruba
